{
    "seed_drop_chance": 1.0, 
    "growth_bonus": 0.025, 
    "seed_drop_bonus": 0.0, 
    "seed_items": [
        {
            "tags": "", 
            "ignoreMeta": false, 
            "item": "mysticalagriculture:silicon_seeds", 
            "meta": 0, 
            "ignoreTags": [
                "*"
            ], 
            "useOreDict": false
        }
    ], 
    "description": {
        "default": "Silicon Seeds.", 
        "translations": {}
    }, 
    "seed_name": "Silicon Seeds", 
    "spawn_chance": 0.0, 
    "bonemeal": false, 
    "enabled": true, 
    "requirement": {
        "min_light": 10, 
        "soils": [
            "farmland_soil"
        ], 
        "conditions": [], 
        "max_light": 16
    }, 
    "texture": {
        "plant_textures": [
            "mysticalagriculture:blocks/crop0", 
            "mysticalagriculture:blocks/crop1", 
            "mysticalagriculture:blocks/crop2", 
            "mysticalagriculture:blocks/crop2", 
            "mysticalagriculture:blocks/crop3", 
            "mysticalagriculture:blocks/crop4", 
            "mysticalagriculture:blocks/crop4", 
            "mysticalagriculture:blocks/silicon_crop"
        ], 
        "render_type": "cross", 
        "seed_texture": "mysticalagriculture:items/silicon_seeds"
    }, 
    "grass_drop_chance": 0.0, 
    "spread_chance": 0.1, 
    "weedable": false, 
    "products": {
        "products": [
            {
                "min": 1, 
                "max": 5, 
                "required": true, 
                "ignoreMeta": false, 
                "item": "mysticalagriculture:silicon_essence", 
                "chance": 0.9, 
                "meta": 0, 
                "ignoreTags": [], 
                "useOreDict": false, 
                "tags": ""
            }, 
            {
                "min": 1, 
                "max": 1, 
                "required": true, 
                "ignoreMeta": false, 
                "item": "mysticalagriculture:fertilized_essence", 
                "chance": 0.005, 
                "meta": 0, 
                "ignoreTags": [], 
                "useOreDict": false, 
                "tags": ""
            }
        ]
    }, 
    "plant_name": "Silicon Crop", 
    "growth_chance": 0.9, 
    "tier": 1, 
    "path": "mod_mysticalagriculture/plants/silicon_plant.json", 
    "aggressive": false, 
    "id": "mysticalagriculture:silicon_plant"
}